ms_peak_picker/fft_patterson_charge_state.py
ms_peak_picker/scan_filter.py
ms_peak_picker/peak_index.py
ms_peak_picker/scan_averaging.py
ms_peak_picker/search.py
ms_peak_picker/base.py
ms_peak_picker/plot.py
ms_peak_picker/version.py
ms_peak_picker/reprofile.py
ms_peak_picker/peak_picker.pyi
ms_peak_picker/utils.py
ms_peak_picker/fticr_denoising.py
ms_peak_picker/peak_set.pyi
ms_peak_picker/peak_set.py
ms_peak_picker/peak_picker.py
ms_peak_picker/__init__.py
ms_peak_picker/peak_statistics.py
ms_peak_picker/smoothing.py
ms_peak_picker/_c/double_vector.cpython-38-x86_64-linux-gnu.so
ms_peak_picker/_c/size_t_vector.c
ms_peak_picker/_c/search.pyx
ms_peak_picker/_c/search.pxd
ms_peak_picker/_c/search.c
ms_peak_picker/_c/fticr_denoising.c
ms_peak_picker/_c/peak_index.pxd
ms_peak_picker/_c/peak_statistics.c
ms_peak_picker/_c/peak_picker.pyx
ms_peak_picker/_c/fticr_denoising.pyx
ms_peak_picker/_c/double_vector.pxd
ms_peak_picker/_c/peak_picker.cpython-38-x86_64-linux-gnu.so
ms_peak_picker/_c/interval_t_vector.pxd
ms_peak_picker/_c/fft_patterson_charge_state.c
ms_peak_picker/_c/peak_picker.c
ms_peak_picker/_c/peak_picker.pxd
ms_peak_picker/_c/fticr_denoising.cpython-38-x86_64-linux-gnu.so
ms_peak_picker/_c/smoother.pxd
ms_peak_picker/_c/smoother.c
ms_peak_picker/_c/peak_set.cpython-38-x86_64-linux-gnu.so
ms_peak_picker/_c/smoother.cpython-38-x86_64-linux-gnu.so
ms_peak_picker/_c/size_t_vector.pyx
ms_peak_picker/_c/double_vector.pyx
ms_peak_picker/_c/fft_patterson_charge_state.pyx
ms_peak_picker/_c/scan_averaging.cpython-38-x86_64-linux-gnu.so
ms_peak_picker/_c/peak_set.pxd
ms_peak_picker/_c/scan_averaging.pyx
ms_peak_picker/_c/peak_statistics.cpython-38-x86_64-linux-gnu.so
ms_peak_picker/_c/size_t_vector.cpython-38-x86_64-linux-gnu.so
ms_peak_picker/_c/peak_index.cpython-38-x86_64-linux-gnu.so
ms_peak_picker/_c/peak_index.pyx
ms_peak_picker/_c/peak_statistics.pxd
ms_peak_picker/_c/peak_set.pyx
ms_peak_picker-0.1.46.dist-info/WHEEL
ms_peak_picker-0.1.46.dist-info/top_level.txt
ms_peak_picker-0.1.46.dist-info/RECORD
ms_peak_picker-0.1.46.dist-info/METADATA
