Metadata-Version: 2.1
Name: ms_peak_picker
Version: 0.1.46
Summary: A library to pick peaks from mass spectral data
Author: Joshua Klein
Author-email: jaklein@bu.edu
Maintainer: Joshua Klein
Maintainer-email: jaklein@bu.edu
License: License :: OSI Approved :: Apache Software License
Classifier: Intended Audience :: Science/Research
Classifier: Programming Language :: Python :: 3.8
Classifier: Programming Language :: Python :: 3.9
Classifier: Programming Language :: Python :: 3.10
Classifier: Programming Language :: Python :: 3.11
Classifier: Topic :: Education
Classifier: Topic :: Scientific/Engineering :: Bio-Informatics
Classifier: Topic :: Scientific/Engineering :: Chemistry
Classifier: Topic :: Software Development :: Libraries
Requires-Dist: numpy
Requires-Dist: scipy
Requires-Dist: six
